nilesh_library/__init__.py
nilesh_library/nilesh_library.py
nilesh_library-1.0.0.dist-info/METADATA
nilesh_library-1.0.0.dist-info/WHEEL
nilesh_library-1.0.0.dist-info/top_level.txt
nilesh_library-1.0.0.dist-info/RECORD
